include/eigen3/signature_of_eigen3_matrix_library
include/eigen3/Eigen/AccelerateSupport
include/eigen3/Eigen/Cholesky
include/eigen3/Eigen/CholmodSupport
include/eigen3/Eigen/Core
include/eigen3/Eigen/Dense
include/eigen3/Eigen/Eigen
include/eigen3/Eigen/Eigenvalues
include/eigen3/Eigen/Geometry
include/eigen3/Eigen/Householder
include/eigen3/Eigen/IterativeLinearSolvers
include/eigen3/Eigen/Jacobi
include/eigen3/Eigen/KLUSupport
include/eigen3/Eigen/LU
include/eigen3/Eigen/MetisSupport
include/eigen3/Eigen/OrderingMethods
include/eigen3/Eigen/PaStiXSupport
include/eigen3/Eigen/PardisoSupport
include/eigen3/Eigen/QR
include/eigen3/Eigen/QtAlignedMalloc
include/eigen3/Eigen/SPQRSupport
include/eigen3/Eigen/SVD
include/eigen3/Eigen/Sparse
include/eigen3/Eigen/SparseCholesky
include/eigen3/Eigen/SparseCore
include/eigen3/Eigen/SparseLU
include/eigen3/Eigen/SparseQR
include/eigen3/Eigen/StdDeque
include/eigen3/Eigen/StdList
include/eigen3/Eigen/StdVector
include/eigen3/Eigen/SuperLUSupport
include/eigen3/Eigen/ThreadPool
include/eigen3/Eigen/UmfPackSupport
include/eigen3/Eigen/src/AccelerateSupport/AccelerateSupport.h
include/eigen3/Eigen/src/AccelerateSupport/InternalHeaderCheck.h
include/eigen3/Eigen/src/Cholesky/InternalHeaderCheck.h
include/eigen3/Eigen/src/Cholesky/LDLT.h
include/eigen3/Eigen/src/Cholesky/LLT.h
include/eigen3/Eigen/src/Cholesky/LLT_LAPACKE.h
include/eigen3/Eigen/src/CholmodSupport/CholmodSupport.h
include/eigen3/Eigen/src/CholmodSupport/InternalHeaderCheck.h
include/eigen3/Eigen/src/Core/ArithmeticSequence.h
include/eigen3/Eigen/src/Core/Array.h
include/eigen3/Eigen/src/Core/ArrayBase.h
include/eigen3/Eigen/src/Core/ArrayWrapper.h
include/eigen3/Eigen/src/Core/Assign.h
include/eigen3/Eigen/src/Core/AssignEvaluator.h
include/eigen3/Eigen/src/Core/Assign_MKL.h
include/eigen3/Eigen/src/Core/BandMatrix.h
include/eigen3/Eigen/src/Core/Block.h
include/eigen3/Eigen/src/Core/CommaInitializer.h
py_ste-1.1.1.dist-info/METADATA
py_ste-1.1.1.dist-info/WHEEL
py_ste-1.1.1.dist-info/RECORD
py_ste-1.1.1.dist-info/licenses/LICENSE
