Metadata-Version: 2.4
Name: py-ste
Version: 1.1.1
Summary: A Python package for evolving unitaries and states under the Schrödinger equation using first-order Suzuki-Trotter and computing switching functions.
Keywords: evolver,evolution,suzuki,trotter,simulation,intergrator,integration,unitary,quantum
Author: Crispin H. W. Barnes, Normann Mertig
Author-Email: "Christopher K. Long" <ckl45@cam.ac.uk>
Maintainer-Email: "Christopher K. Long" <ckl45@cam.ac.uk>
License-Expression: Apache-2.0
License-File: LICENSE
Classifier: Programming Language :: Python :: 3
Classifier: Programming Language :: Python :: 3.8
Classifier: Programming Language :: Python :: 3.9
Classifier: Programming Language :: Python :: 3.10
Classifier: Programming Language :: Python :: 3.11
Classifier: Programming Language :: Python :: 3.12
Classifier: Programming Language :: Python :: 3.13
Classifier: Programming Language :: Python :: 3.14
Classifier: Development Status :: 5 - Production/Stable
Classifier: Intended Audience :: Science/Research
Classifier: Natural Language :: English
Classifier: Operating System :: OS Independent
Classifier: Topic :: Scientific/Engineering :: Physics
Classifier: Topic :: Scientific/Engineering :: Quantum Computing
Project-URL: Homepage, https://github.com/Christopher-K-Long/PySTE
Project-URL: Documentation, https://PySTE.readthedocs.io/
Project-URL: Issues, https://github.com/Christopher-K-Long/PySTE/issues
Project-URL: Changelog, https://github.com/Christopher-K-Long/PySTE/blob/main/ChangeLog.md
Requires-Python: >=3.8
Requires-Dist: numpy<3,>=1.21
